llmc/__init__.py
llmc/__main__.py
llmc/cli.py
llmc-0.1.2.dist-info/LICENSE
llmc-0.1.2.dist-info/METADATA
llmc-0.1.2.dist-info/WHEEL
llmc-0.1.2.dist-info/entry_points.txt
llmc-0.1.2.dist-info/RECORD
