Metadata-Version: 2.1
Name: llmc
Version: 0.1.2
Summary: Using LLMs for compilers
Author: Kaiser Pister
Author-email: pisterk@gmail.com
Requires-Python: >=3.9,<4.0
Classifier: Programming Language :: Python :: 3
Classifier: Programming Language :: Python :: 3.9
Classifier: Programming Language :: Python :: 3.10
Classifier: Programming Language :: Python :: 3.11
Requires-Dist: openai (>=0.27.4,<0.28.0)
